terminalmuseum/__init__.py
terminalmuseum/data/36029.jpg
terminalmuseum/data/36131.jpg
terminalmuseum/data/37788.jpg
terminalmuseum/data/37801.jpg
terminalmuseum/data/37942.jpg
terminalmuseum/data/39668.jpg
terminalmuseum/data/39901.jpg
terminalmuseum/data/39915.jpg
terminalmuseum/data/39936.jpg
terminalmuseum/data/40055.jpg
terminalmuseum/data/40081.jpg
terminalmuseum/data/42716.jpg
terminalmuseum/data/435600.jpg
terminalmuseum/data/435621.jpg
terminalmuseum/data/435641.jpg
terminalmuseum/data/435702.jpg
terminalmuseum/data/435728.jpg
terminalmuseum/data/435739.jpg
terminalmuseum/data/435802.jpg
terminalmuseum/data/435809.jpg
terminalmuseum/data/435817.jpg
terminalmuseum/data/435826.jpg
terminalmuseum/data/435839.jpg
terminalmuseum/data/435844.jpg
terminalmuseum/data/435851.jpg
terminalmuseum/data/435853.jpg
terminalmuseum/data/435868.jpg
terminalmuseum/data/435876.jpg
terminalmuseum/data/435882.jpg
terminalmuseum/data/435888.jpg
terminalmuseum/data/435896.jpg
terminalmuseum/data/435908.jpg
terminalmuseum/data/435962.jpg
terminalmuseum/data/435984.jpg
terminalmuseum/data/436002.jpg
terminalmuseum/data/436037.jpg
terminalmuseum/data/436095.jpg
terminalmuseum/data/436101.jpg
terminalmuseum/data/436105.jpg
terminalmuseum/data/436106.jpg
terminalmuseum/data/436121.jpg
terminalmuseum/data/436244.jpg
terminalmuseum/data/436253.jpg
terminalmuseum/data/436282.jpg
terminalmuseum/data/436323.jpg
terminalmuseum/data/436440.jpg
terminalmuseum/data/436504.jpg
terminalmuseum/data/436516.jpg
terminalmuseum/data/436528.jpg
terminalmuseum/data/436532.jpg
terminalmuseum/data/436535.jpg
terminalmuseum/data/436545.jpg
terminalmuseum/data/436573.jpg
terminalmuseum/data/436575.jpg
terminalmuseum/data/436579.jpg
terminalmuseum/data/436603.jpg
terminalmuseum/data/436622.jpg
terminalmuseum/data/436658.jpg
terminalmuseum/data/436792.jpg
terminalmuseum/data/436819.jpg
terminalmuseum/data/436838.jpg
terminalmuseum/data/436839.jpg
terminalmuseum/data/436840.jpg
terminalmuseum/data/436851.jpg
terminalmuseum-0.1.1.dist-info/entry_points.txt
terminalmuseum-0.1.1.dist-info/LICENSE
terminalmuseum-0.1.1.dist-info/WHEEL
terminalmuseum-0.1.1.dist-info/METADATA
terminalmuseum-0.1.1.dist-info/RECORD
